stagedfright.py
pareto/__init__.py
pareto/conftest.py
pareto/case_studies/__init__.py
pareto/case_studies/operational_generic_case_study.xlsx
pareto/case_studies/stochastic_toy_study.xlsx
pareto/case_studies/strategic_permian_demo.xlsx
pareto/case_studies/strategic_small_case_study.xlsx
pareto/case_studies/strategic_toy_case_study.xlsx
pareto/case_studies/strategic_treatment_demo.xlsx
pareto/case_studies/strategic_treatment_demo_surrogates.xlsx
pareto/case_studies/workshop_baseline_all_data.xlsx
pareto/models_extra/__init__.py
pareto/models_extra/CM_module/__init__.py
pareto/models_extra/CM_module/run_base.py
pareto/models_extra/CM_module/run_infrastructure_analysis.py
pareto/models_extra/CM_module/run_optimal_desal.py
pareto/models_extra/CM_module/case_studies/CM_integrated_desalination_demo.xlsx
pareto/models_extra/CM_module/case_studies/CM_large_permian.xlsx
pareto/models_extra/CM_module/case_studies/CM_small_permian.xlsx
pareto/models_extra/CM_module/case_studies/__init__.py
pareto/models_extra/CM_module/cm_utils/__init__.py
pareto/models_extra/CM_module/cm_utils/data_parser.py
pareto/models_extra/CM_module/cm_utils/gen_utils.py
pareto/models_extra/CM_module/cm_utils/opt_utils.py
pareto/models_extra/CM_module/cm_utils/run_utils.py
pareto/models_extra/CM_module/cm_utils/spec_utils.py
pareto/models_extra/CM_module/models/__init__.py
pareto/models_extra/CM_module/models/qcp_br.py
pareto/models_extra/desalination_models/MD_single_stage_continuous_recirculation.py
pareto/models_extra/desalination_models/__init__.py
pareto/models_extra/desalination_models/mee_mvr.py
pareto/models_extra/integrate_desal/__init__.py
pareto/models_extra/integrate_desal/integrated_models/__init__.py
pareto/models_extra/integrate_desal/integrated_models/backcalculate_mvr_design.py
pareto/models_extra/integrate_desal/integrated_models/integrated_optimization_md.py
pareto/models_extra/integrate_desal/integrated_models/integrated_optimization_mvr.py
project_pareto-1.1.0.dist-info/licenses/LICENSE.md
project_pareto-1.1.0.dist-info/METADATA
project_pareto-1.1.0.dist-info/WHEEL
project_pareto-1.1.0.dist-info/entry_points.txt
project_pareto-1.1.0.dist-info/top_level.txt
project_pareto-1.1.0.dist-info/RECORD
