Metadata-Version: 2.4
Name: project-pareto
Version: 1.1.0
Summary: Project PARETO - The Produced Water Optimization Initiative
Home-page: https://www.project-pareto.org
Author: PARETO team
Maintainer: Keith Beattie
Maintainer-email: ksbeattie@lbl.gov
License: BSD
Keywords: PARETO,produced water,optimization,process modeling,chemical engineering,water management
Platform: windows
Platform: linux
Classifier: Development Status :: 3 - Alpha
Classifier: Intended Audience :: End Users/Desktop
Classifier: Intended Audience :: Science/Research
Classifier: License :: OSI Approved :: BSD License
Classifier: Natural Language :: English
Classifier: Operating System :: Microsoft :: Windows
Classifier: Operating System :: Unix
Classifier: Programming Language :: Python
Classifier: Programming Language :: Python :: 3
Classifier: Programming Language :: Python :: 3.8
Classifier: Programming Language :: Python :: 3.9
Classifier: Programming Language :: Python :: 3.10
Classifier: Programming Language :: Python :: 3.11
Classifier: Programming Language :: Python :: Implementation :: CPython
Classifier: Topic :: Scientific/Engineering :: Mathematics
Classifier: Topic :: Scientific/Engineering :: Chemistry
Classifier: Topic :: Software Development :: Libraries :: Python Modules
Classifier: Programming Language :: Python :: 3 :: Only
Requires-Python: >=3.8, <4
License-File: LICENSE.md
Requires-Dist: pyomo>=6.2
Requires-Dist: numpy
Requires-Dist: pandas<3,>=2
Requires-Dist: openpyxl
Requires-Dist: idaes-pse==2.5
Requires-Dist: requests
Requires-Dist: plotly==5.11.0
Requires-Dist: kaleido
Requires-Dist: ipywidgets>=8.0.0
Requires-Dist: tensorflow==2.13.0
Requires-Dist: omlt==1.1
Requires-Dist: pyproj; python_version >= "3.9"
Provides-Extra: testing
Requires-Dist: pytest; extra == "testing"
Requires-Dist: packaging; extra == "testing"
Requires-Dist: pyyaml; extra == "testing"
Dynamic: author
Dynamic: classifier
Dynamic: description
Dynamic: description-content-type
Dynamic: home-page
Dynamic: keywords
Dynamic: license
Dynamic: license-file
Dynamic: maintainer
Dynamic: maintainer-email
Dynamic: platform
Dynamic: provides-extra
Dynamic: requires-dist
Dynamic: requires-python
Dynamic: summary
